{"name":"Create a user so that he can login into COVID THE GAME application","id":"user-creation--complete-some-challenges-and-check-the-leaderboard;create-a-user-so-that-he-can-login-into-covid-the-game-application","testSteps":[{"number":1,"description":"Given User is on home page of COVID application","duration":14395,"startTime":"2022-05-21T15:13:33.437324+10:00[Australia/Sydney]","screenshots":[{"screenshot":"5d7c4e8324919d3612db9ae1159624888f4bdd49409cc3b489fac8c723db9326.png","timeStamp":1653110027832}],"result":"SUCCESS","precondition":false,"level":0,"children":[{"number":2,"description":"Open application","duration":13989,"startTime":"2022-05-21T15:13:33.830275+10:00[Australia/Sydney]","screenshots":[{"screenshot":"5d7c4e8324919d3612db9ae1159624888f4bdd49409cc3b489fac8c723db9326.png","timeStamp":1653110027818}],"result":"SUCCESS","precondition":false,"level":1}]},{"number":3,"description":"When he clicks on Register button, Sign Up page is displayed","duration":472,"startTime":"2022-05-21T15:13:47.835680+10:00[Australia/Sydney]","screenshots":[{"screenshot":"145802c9a54790a9c5facffcd8729b88567fe178513cd12371664f6ec94c8c04.png","timeStamp":1653110028308}],"result":"SUCCESS","precondition":false,"level":0,"children":[{"number":4,"description":"Click register","duration":452,"startTime":"2022-05-21T15:13:47.849607+10:00[Australia/Sydney]","screenshots":[{"screenshot":"145802c9a54790a9c5facffcd8729b88567fe178513cd12371664f6ec94c8c04.png","timeStamp":1653110028300}],"result":"SUCCESS","precondition":false,"level":1}]},{"number":5,"description":"And he enters username password and repeat password and clicks on Sign Up button to register","duration":1189,"startTime":"2022-05-21T15:13:48.311474+10:00[Australia/Sydney]","screenshots":[{"screenshot":"e6795060db5be35db52d113a123bf29666e57166dc106ad0cbc62a5b47df5a32.png","timeStamp":1653110029500}],"result":"SUCCESS","precondition":false,"level":0,"children":[{"number":6,"description":"Enter username","duration":437,"startTime":"2022-05-21T15:13:48.326470+10:00[Australia/Sydney]","screenshots":[{"screenshot":"9e298dfbddc8a2bda0186694351a67aa449a7395741e0711e5143fc104924f78.png","timeStamp":1653110028763}],"result":"SUCCESS","precondition":false,"level":1},{"number":7,"description":"Enter password","duration":247,"startTime":"2022-05-21T15:13:48.765133+10:00[Australia/Sydney]","screenshots":[{"screenshot":"9e298dfbddc8a2bda0186694351a67aa449a7395741e0711e5143fc104924f78.png","timeStamp":1653110028767},{"screenshot":"13c3bf6fac7c40c4e275d5fab538be7576684e626a55a4d8195c09127c5a29e3.png","timeStamp":1653110029012}],"result":"SUCCESS","precondition":false,"level":1},{"number":8,"description":"Repeat password","duration":214,"startTime":"2022-05-21T15:13:49.016980+10:00[Australia/Sydney]","screenshots":[{"screenshot":"13c3bf6fac7c40c4e275d5fab538be7576684e626a55a4d8195c09127c5a29e3.png","timeStamp":1653110029019},{"screenshot":"75a7bbedc57b91d57960486a482002ca5d552b1df223e220c942bd3d2b695490.png","timeStamp":1653110029231}],"result":"SUCCESS","precondition":false,"level":1},{"number":9,"description":"Sign up","duration":262,"startTime":"2022-05-21T15:13:49.233281+10:00[Australia/Sydney]","screenshots":[{"screenshot":"75a7bbedc57b91d57960486a482002ca5d552b1df223e220c942bd3d2b695490.png","timeStamp":1653110029236},{"screenshot":"e6795060db5be35db52d113a123bf29666e57166dc106ad0cbc62a5b47df5a32.png","timeStamp":1653110029495}],"result":"SUCCESS","precondition":false,"level":1}]},{"number":10,"description":"Then User should be registered and should be able to login into application","duration":15952,"startTime":"2022-05-21T15:13:49.501877+10:00[Australia/Sydney]","screenshots":[{"screenshot":"b542136a523281d122b4aceab5b062cd654b3414d32c8038573a71cee5abc21f.png","timeStamp":1653110045454}],"result":"SUCCESS","precondition":false,"level":0,"children":[{"number":11,"description":"Enter username to login","duration":2009,"startTime":"2022-05-21T15:13:49.506389+10:00[Australia/Sydney]","screenshots":[{"screenshot":"44fd8c4220a1994c11c9bc7f64dde336c73236db36cedd6fdea2a9789a4f5b3e.png","timeStamp":1653110031515}],"result":"SUCCESS","precondition":false,"level":1},{"number":12,"description":"Enter password to login","duration":213,"startTime":"2022-05-21T15:13:51.517229+10:00[Australia/Sydney]","screenshots":[{"screenshot":"44fd8c4220a1994c11c9bc7f64dde336c73236db36cedd6fdea2a9789a4f5b3e.png","timeStamp":1653110031520},{"screenshot":"ff0cbf00383aa71fba6cbc74e3e53e8388128292a2a49deb37455bf81f0cea79.png","timeStamp":1653110031730}],"result":"SUCCESS","precondition":false,"level":1},{"number":13,"description":"Click login button","duration":384,"startTime":"2022-05-21T15:13:54.751794+10:00[Australia/Sydney]","screenshots":[{"screenshot":"0a134a36e22d25caf4819fea14d93bb11284e294dd3c40171a5d3be5cd019388.png","timeStamp":1653110034919},{"screenshot":"1b94f102d085be86655cc2d507fa80b7a07ed1c86a012b2f8628f3e87398dada.png","timeStamp":1653110035136}],"result":"SUCCESS","precondition":false,"level":1},{"number":14,"description":"Click start journey button","duration":7023,"startTime":"2022-05-21T15:13:55.137810+10:00[Australia/Sydney]","screenshots":[{"screenshot":"1b94f102d085be86655cc2d507fa80b7a07ed1c86a012b2f8628f3e87398dada.png","timeStamp":1653110035146},{"screenshot":"bd7732a778a1a57a0d69592a15264e3e7fc2ad0fc92fd76660786dedbdacd5b9.png","timeStamp":1653110042161}],"result":"SUCCESS","precondition":false,"level":1},{"number":15,"description":"Verify successfull login","duration":3284,"startTime":"2022-05-21T15:14:02.163953+10:00[Australia/Sydney]","screenshots":[{"screenshot":"bd7732a778a1a57a0d69592a15264e3e7fc2ad0fc92fd76660786dedbdacd5b9.png","timeStamp":1653110042166},{"screenshot":"b542136a523281d122b4aceab5b062cd654b3414d32c8038573a71cee5abc21f.png","timeStamp":1653110045448}],"result":"SUCCESS","precondition":false,"level":1}]}],"userStory":{"id":"user-creation--complete-some-challenges-and-check-the-leaderboard","storyName":"User Creation, complete some challenges and check the leaderboard","displayName":"User Creation, complete some challenges and check the leaderboard","path":"covid19.feature","type":"feature"},"featureTag":{"name":"User Creation, complete some challenges and check the leaderboard","type":"feature","displayName":"User Creation, complete some challenges and check the leaderboard"},"title":"Create a user so that he can login into COVID THE GAME application","description":"","tags":[{"name":"RegressionTest","type":"tag","displayName":"RegressionTest"},{"name":"User Creation, complete some challenges and check the leaderboard","type":"feature","displayName":"User Creation, complete some challenges and check the leaderboard"}],"startTime":"2022-05-21T15:13:33.331690+10:00[Australia/Sydney]","duration":32126,"projectKey":"","sessionId":"13b793ad8154e403d2ef36ceb92e2f23","driver":"chrome","isManualTestingUpToDate":false,"manual":false,"testSource":"Cucumber","result":"SUCCESS"}